pw_simple_scraper/__init__.py
pw_simple_scraper/browser.py
pw_simple_scraper/core.py
pw_simple_scraper/model.py
pw_simple_scraper/utils.py
pw_simple_scraper/strategies/__init__.py
pw_simple_scraper/strategies/mobile.py
pw_simple_scraper/strategies/proxy.py
pw_simple_scraper/strategies/stealth.py
pw_simple_scraper-0.1.2.dist-info/licenses/LICENSE
pw_simple_scraper-0.1.2.dist-info/METADATA
pw_simple_scraper-0.1.2.dist-info/WHEEL
pw_simple_scraper-0.1.2.dist-info/top_level.txt
pw_simple_scraper-0.1.2.dist-info/RECORD
