Metadata-Version: 2.4
Name: pw-simple-scraper
Version: 0.1.2
Summary: A simple and light Playwright-based scraper
Author-email: elecbrandy <elecbrandy@gmail.com>
License: MIT
Project-URL: Homepage, https://github.com/elecbrandy/pw-simple-scraper
Project-URL: Repository, https://github.com/elecbrandy/pw-simple-scraper
Project-URL: Issues, https://github.com/elecbrandy/pw-simple-scraper/issues
Keywords: playwright,scraping,web-scraping,automation,crawler
Classifier: Development Status :: 4 - Beta
Classifier: Intended Audience :: Developers
Classifier: License :: OSI Approved :: MIT License
Classifier: Operating System :: OS Independent
Classifier: Programming Language :: Python :: 3
Classifier: Programming Language :: Python :: 3.9
Classifier: Programming Language :: Python :: 3.10
Classifier: Programming Language :: Python :: 3.11
Classifier: Programming Language :: Python :: 3.12
Classifier: Topic :: Internet :: WWW/HTTP
Classifier: Topic :: Software Development :: Libraries :: Python Modules
Requires-Python: >=3.9
License-File: LICENSE
Requires-Dist: playwright>=1.44
Requires-Dist: nest_asyncio>=1.5.6
Provides-Extra: dev
Requires-Dist: pytest; extra == "dev"
Requires-Dist: black; extra == "dev"
Requires-Dist: isort; extra == "dev"
Dynamic: license-file
